{
  "project_info": {
    "project_number": "144905320810",
    "project_id": "social-sdu",
    "storage_bucket": "social-sdu.appspot.com"
  },
  "client": [
    {
      "client_info": {
        "mobilesdk_app_id": "1:144905320810:android:3c10b8963fe5b736800d13",
        "android_client_info": {
          "package_name": "com.example.youtube_clone"
        }
      },
      "oauth_client": [],
      "api_key": [
        {
          "current_key": "AIzaSyBnoGrdtLySFOBpJtRhIHjAsAXjnk3ybRg"
        }
      ],
      "services": {
        "appinvite_service": {
          "other_platform_oauth_client": []
        }
      }
    }
  ],
  "configuration_version": "1"
}